{
  "main": {
    "id": "1efd9dcd2bcfd219",
    "type": "split",
    "children": [
      {
        "id": "c1d0cd442545f954",
        "type": "tabs",
        "children": [
          {
            "id": "b7a8a86b68c1c05d",
            "type": "leaf",
            "state": {
              "type": "markdown",
              "state": {
                "file": "Work/Epos Now/Projects/Billing 2.0/Initial project Summary.md",
                "mode": "source",
                "backlinks": true,
                "source": false
              }
            }
          }
        ]
      }
    ],
    "direction": "vertical"
  },
  "left": {
    "id": "6ad620901bcdb3f7",
    "type": "split",
    "children": [
      {
        "id": "e40b3c4d91bee790",
        "type": "tabs",
        "children": [
          {
            "id": "84f09f82255e9603",
            "type": "leaf",
            "state": {
              "type": "file-explorer",
              "state": {
                "sortOrder": "alphabetical"
              }
            }
          },
          {
            "id": "1ea3590a14210450",
            "type": "leaf",
            "state": {
              "type": "search",
              "state": {
                "query": "",
                "matchingCase": false,
                "explainSearch": false,
                "collapseAll": false,
                "extraContext": false,
                "sortOrder": "alphabetical"
              }
            }
          },
          {
            "id": "5ba73917e0718a52",
            "type": "leaf",
            "state": {
              "type": "bookmarks",
              "state": {}
            }
          }
        ]
      }
    ],
    "direction": "horizontal",
    "width": 252.5
  },
  "right": {
    "id": "fdaff6413e2567d3",
    "type": "split",
    "children": [
      {
        "id": "08c1dee0c3340945",
        "type": "tabs",
        "children": [
          {
            "id": "7060937d5c5e0efa",
            "type": "leaf",
            "state": {
              "type": "backlink",
              "state": {
                "file": "Work/Epos Now/Projects/Billing 2.0/Initial project Summary.md",
                "collapseAll": false,
                "extraContext": false,
                "sortOrder": "alphabetical",
                "showSearch": false,
                "searchQuery": "",
                "backlinkCollapsed": false,
                "unlinkedCollapsed": false
              }
            }
          },
          {
            "id": "fc0cd75f4a9683db",
            "type": "leaf",
            "state": {
              "type": "outgoing-link",
              "state": {
                "file": "Work/Epos Now/Projects/Billing 2.0/Initial project Summary.md",
                "linksCollapsed": false,
                "unlinkedCollapsed": true
              }
            }
          },
          {
            "id": "2d4c80fb509c0322",
            "type": "leaf",
            "state": {
              "type": "tag",
              "state": {
                "sortOrder": "frequency",
                "useHierarchy": true
              }
            }
          },
          {
            "id": "5c557ac4eadf43f8",
            "type": "leaf",
            "state": {
              "type": "outline",
              "state": {
                "file": "Work/Epos Now/Projects/Billing 2.0/Initial project Summary.md"
              }
            }
          },
          {
            "id": "fa36be50c8f2cff3",
            "type": "leaf",
            "state": {
              "type": "git-view",
              "state": {}
            }
          },
          {
            "id": "cae46ad2a2467dc3",
            "type": "leaf",
            "state": {
              "type": "advanced-tables-toolbar",
              "state": {}
            }
          },
          {
            "id": "ff86658df7411e6f",
            "type": "leaf",
            "state": {
              "type": "all-properties",
              "state": {
                "sortOrder": "frequency"
              }
            }
          }
        ],
        "currentTab": 5
      }
    ],
    "direction": "horizontal",
    "width": 200,
    "collapsed": true
  },
  "left-ribbon": {
    "hiddenItems": {
      "switcher:Open quick switcher": false,
      "graph:Open graph view": false,
      "canvas:Create new canvas": false,
      "daily-notes:Open today's daily note": false,
      "templates:Insert template": false,
      "command-palette:Open command palette": false,
      "table-editor-obsidian:Advanced Tables Toolbar": false,
      "workspaces:Manage workspace layouts": false
    }
  },
  "active": "b7a8a86b68c1c05d",
  "lastOpenFiles": [
    "Work/Epos Now/Images/Payments Process.png",
    "Work/Epos Now/Images/Pasted image 20231025094810.png",
    "Work/Epos Now/Images/Pasted image 20231025092344.png",
    "Work/Epos Now/Images/620cdf81d2478-image.png",
    "Work/Epos Now/Projects/Billing 2.0/Initial project Summary.md",
    "Work/Epos Now/Documentation/Processes/Intergrations/API REST Endpoints.md",
    "SalesForce/Apex/SOQL & SOSL/SOQL & SOSL Queries.md",
    "Work/Epos Now/Projects/Billing 2.0",
    "Work/Epos Now/Projects",
    "Random Notes/Studies/JRE clips.md",
    "Work/Epos Now/Documentation/Processes/Async Processing/Async Request Custom Object.md",
    "Random Notes/Studies",
    "Random Notes",
    "Gym",
    "Work/Epos Now/Documentation/DataTable/Key Data.md",
    "Work/Epos Now/Documentation/Helper methods.md",
    "Work/Epos Now/Documentation/DataTable",
    "Work/Epos Now/Documentation/Processes/Sales Process.md",
    "Work/Epos Now/Documentation/Processes/Async Processing/TriggerOnAsyncAttempt.md",
    "Work/Epos Now/Documentation/Processes/Async Processing/TriggerOnAsyncRequest.md",
    "Work/Epos Now/Documentation/Processes/Async Processing",
    "Work/Epos Now/Documentation/Processes/Epos Now Payments/Epos Now Payments.md",
    "Work/Epos Now/Documentation/Processes/Intergrations",
    "Work/Epos Now/Documentation/Processes/Epos Now Payments/Swap it Process.md",
    "Work/Epos Now/Documentation/Processes/Epos Now Payments/KYC Process.md",
    "Work/Epos Now/Documentation/Processes/Epos Now Payments/Dispatch & Serials.md",
    "Work/Epos Now/Documentation/Processes/Epos Now Payments/Approval Process.md",
    "Work/Epos Now/Documentation/Triggers.md",
    "Work/Epos Now/Documentation/Pricing and Propositions.md",
    "Work/Epos Now/Documentation/Processes/Epos Now Payments/Sales Process.md",
    "Work/Epos Now/Documentation/Processes/Billing/Failed Payments.md",
    "Work/Epos Now/Documentation/Processes/Epos Now Payments",
    "Work/Epos Now/Documentation/Processes/Billing/Payment Premium.md",
    "Work/Epos Now/Documentation/Processes/Billing/Refunds.md",
    "Work/Epos Now/Documentation/Processes/Billing/Repeat Billing.md",
    "Work/Epos Now/Documentation/Processes/Billing",
    "Trading/EmperorBTC/Chapter one - BulletProof Your Trading.md",
    "Untitled.md",
    "Food&Cooking/Cookware/Good Brands.md",
    "Trading/Images/Pasted image 20230903131455.png",
    "Trading/Images/Pasted image 20230903131102.png",
    "Trading/Images/Pasted image 20230903130154.png",
    "Trading/Images/Pasted image 20230903125329.png",
    "Trading/Images/Pasted image 20230903123054.png",
    "Trading/Images/Pasted image 20230903121232.png",
    "Untitled.canvas"
  ]
}